{
  "name": "amla",
  "version": "1.0.0",
  "color": {
    "primary": { "50": "#EEF8F2", "100": "#D7F0E1", "200": "#AFE1C3", "300": "#7FCFA1", "400": "#52BE83", "500": "#2EAC69", "600": "#1F8D55", "700": "#186E44", "800": "#125235", "900": "#0D3B27" },
    "accent":  { "500": "#FFA33E" },
    "neutral": { "50": "#F7F7F8", "100": "#EEEFF1", "200": "#E2E4E8", "300": "#C9CDD3", "400": "#A3AAB4", "500": "#7B8594", "600": "#5C6573", "700": "#434A56", "800": "#2E333C", "900": "#1C2128" },
    "success": { "500": "#12B76A" },
    "warning": { "500": "#F79009" },
    "danger":  { "500": "#D92D20" }
  },
  "radius": { "sm": "6px", "md": "10px", "lg": "14px", "xl": "18px" },
  "shadow": { "sm": "0 1px 2px rgba(16, 24, 40, 0.06)", "md": "0 4px 10px rgba(16, 24, 40, 0.08)", "lg": "0 12px 20px rgba(16, 24, 40, 0.12)" },
  "typography": {
    "fontFamily": { "base": "Inter, ui-sans-serif, system-ui, -apple-system, Segoe UI, Roboto" },
    "size": { "xs": "12px", "sm": "14px", "md": "16px", "lg": "18px", "xl": "20px", "2xl": "24px", "3xl": "30px" },
    "lineHeight": { "tight": "1.2", "snug": "1.35", "normal": "1.5" }
  }
}